Workbook

Sheet MENU
A1: AGREGADOR DE DADOS – DECLARAÇÃO DE IMPOSTO DE RENDA
A2: Organize, valide e consolide as informações para a sua declaração anual (IRPF).
B4: Navegue pelas seções:
B6: 1. Dados pessoais | C6: Identificação do declarante, endereço e ocupação.
B8: 2. Dependentes | C8: Cadastro de dependentes com parentesco e CPF validados.
B10: 3. Rendimentos | C10: Salários, aluguéis, rendimentos isentos e de tributação exclusiva.
B12: 4. Despesas dedutíveis | C12: Saúde, educação, previdência e pensão alimentícia.
B14: 5. Bens e direitos | C14: Imóveis, veículos, investimentos — saldo do ano anterior e atual.
B16: 6. Contas bancárias | C16: Contas com banco selecionado da lista oficial de códigos.
B18: 7. Resumo consolidado | C18: Totais calculados automaticamente para conferência.
B20: 8. Links úteis | C20: Atalhos para Receita Federal, e-CAC e programa do IRPF.
B23: Legenda
B24: Células amarelas | C24: Campos para você preencher (texto azul). Listas suspensas e validações impedem dados inválidos.
B25: Células cinza | C25: Calculadas automaticamente por fórmulas — não editar.
B26: 1ª linha de cada tabela | C26: É um EXEMPLO de preenchimento: substitua pelos seus dados ou apague.

Sheet DADOS_PESSOAIS
A1: 1. DADOS PESSOAIS DO DECLARANTE
A2: Preencha as células amarelas.
A3: ◄ Voltar ao Menu
A5: Nome completo | B5: Maria da Silva
A6: CPF (somente números) | B6: 12345678909 | C6: =IF(B6="","",IF(AND(LEN(B6)=11,ISNUMBER(--B6)),"✔ formato válido","✘ verifique o CPF")) -> ✔ formato válido
A7: Data de nascimento | B7: 33013 | C7: =IF(B7="","","Idade: "&DATEDIF(B7,TODAY(),"y")&" anos") -> Idade: 36 anos
A8: Título de eleitor
A9: Endereço | B9: Rua Exemplo, 100
A10: Cidade / UF | B10: Petrópolis / RJ
A11: CEP (somente números) | B11: 25600000
A12: E-mail | B12: maria@email.com
A13: Celular | B13: (24) 99999-0000
A14: Ocupação principal | B14: Analista
A15: Declarou IR no ano anterior? | B15: Sim
A16: Possui dependentes? | B16: Sim
A18: Os valores atuais são de EXEMPLO — substitua pelos seus dados.

Sheet DEPENDENTES
A1: 2. DEPENDENTES
A2: Cada dependente precisa de CPF próprio. Parentesco segue as categorias da Receita Federal.
A3: ◄ Voltar ao Menu
A5: Nome do dependente | B5: CPF (somente números) | C5: Parentesco | D5: Data de nascimento | E5: Idade
A6: João da Silva | B6: 98765432100 | C6: Filho(a)/Enteado(a) até 21 anos | D6: 42073 | E6: =IF(D6="","",DATEDIF(D6,TODAY(),"y")) -> 11
E7: =IF(D7="","",DATEDIF(D7,TODAY(),"y"))
E8: =IF(D8="","",DATEDIF(D8,TODAY(),"y"))
E9: =IF(D9="","",DATEDIF(D9,TODAY(),"y"))
E10: =IF(D10="","",DATEDIF(D10,TODAY(),"y"))
E11: =IF(D11="","",DATEDIF(D11,TODAY(),"y"))
E12: =IF(D12="","",DATEDIF(D12,TODAY(),"y"))
E13: =IF(D13="","",DATEDIF(D13,TODAY(),"y"))
E14: =IF(D14="","",DATEDIF(D14,TODAY(),"y"))
E15: =IF(D15="","",DATEDIF(D15,TODAY(),"y"))
E16: =IF(D16="","",DATEDIF(D16,TODAY(),"y"))
E17: =IF(D17="","",DATEDIF(D17,TODAY(),"y"))
E18: =IF(D18="","",DATEDIF(D18,TODAY(),"y"))
... E105: =IF(D105="","",DATEDIF(D105,TODAY(),"y"))

Sheet RENDIMENTOS
A1: 3. RENDIMENTOS RECEBIDOS
A2: Use os valores do Informe de Rendimentos fornecido pela fonte pagadora.
A3: ◄ Voltar ao Menu
A5: Fonte pagadora | B5: CNPJ/CPF da fonte (somente números) | C5: Tipo de rendimento | D5: Valor recebido no ano (R$) | E5: Contribuição previdenciária (R$) | F5: IR retido na fonte (R$) | G5: 13º salário (R$)
A6: Empresa Exemplo Ltda. | B6: 12345678000190 | C6: Tributável | D6: 60000 | E6: 6600 | F6: 4200 | G6: 5000

Sheet DESPESAS
A1: 4. DESPESAS DEDUTÍVEIS
A2: Guarde recibos e notas fiscais: o CPF/CNPJ do prestador é obrigatório na declaração.
A3: ◄ Voltar ao Menu
A5: Tipo de despesa | B5: Prestador / instituição | C5: CPF/CNPJ do prestador | D5: Beneficiário (titular ou dependente) | E5: Valor pago (R$) | F5: Valor reembolsado (R$)
A6: Saúde (médico, dentista, plano) | B6: Clínica Exemplo | C6: 11222333000181 | D6: Titular | E6: 850 | F6: 0

Sheet BENS_DIREITOS
A1: 5. BENS E DIREITOS
A2: Informe o valor de aquisição (custo), não o valor de mercado.
A3: ◄ Voltar ao Menu
A5: Grupo | B5: Descrição do bem | C5: Situação em 31/12 do ano anterior (R$) | D5: Situação em 31/12 do ano-calendário (R$) | E5: Variação (R$) | F5: Observações
A6: 02 - Bens móveis (veículos etc.) | B6: Automóvel modelo X, ano 2020, placa ABC1D23 | C6: 45000 | D6: 45000 | E6: =IF(AND(C6="",D6=""),"",D6-C6) -> 0
E7: =IF(AND(C7="",D7=""),"",D7-C7)
E8: =IF(AND(C8="",D8=""),"",D8-C8)
E9: =IF(AND(C9="",D9=""),"",D9-C9)
E10: =IF(AND(C10="",D10=""),"",D10-C10)
E11: =IF(AND(C11="",D11=""),"",D11-C11)
E12: =IF(AND(C12="",D12=""),"",D12-C12)
E13: =IF(AND(C13="",D13=""),"",D13-C13)
E14: =IF(AND(C14="",D14=""),"",D14-C14)
E15: =IF(AND(C15="",D15=""),"",D15-C15)
E16: =IF(AND(C16="",D16=""),"",D16-C16)
E17: =IF(AND(C17="",D17=""),"",D17-C17)
E18: =IF(AND(C18="",D18=""),"",D18-C18)
... E105: =IF(AND(C105="",D105=""),"",D105-C105)

Sheet CONTAS_BANCARIAS
A1: 6. CONTAS BANCÁRIAS
A2: Saldos em 31/12 conforme extrato/informe do banco.
A3: ◄ Voltar ao Menu
A5: Banco | B5: Tipo de conta | C5: Agência | D5: Número da conta | E5: Saldo 31/12 ano anterior (R$) | F5: Saldo 31/12 ano-calendário (R$) | G5: Rendimento no ano (R$)
A6: 260 - Nubank | B6: Conta corrente | C6: 0001 | D6: 1234567-8 | E6: 1500 | F6: 2300 | G6: 0

Sheet RESUMO
A1: 7. RESUMO CONSOLIDADO
A2: Totais calculados automaticamente a partir das demais abas. Não editar.
A3: ◄ Voltar ao Menu
A5: RENDIMENTOS
A6: Rendimentos tributáveis | B6: =SUMIFS(RENDIMENTOS!D6:D105,RENDIMENTOS!C6:C105,"Tributável") -> 60000
A7: Rendimentos isentos e não tributáveis | B7: =SUMIFS(RENDIMENTOS!D6:D105,RENDIMENTOS!C6:C105,"Isento e não tributável") -> 0
A8: Rendimentos de tributação exclusiva | B8: =SUMIFS(RENDIMENTOS!D6:D105,RENDIMENTOS!C6:C105,"Tributação exclusiva/definitiva") -> 0
A9: Contribuição previdenciária oficial | B9: =SUM(RENDIMENTOS!E6:E105) -> 6600
A10: Imposto retido na fonte | B10: =SUM(RENDIMENTOS!F6:F105) -> 4200
A12: DESPESAS DEDUTÍVEIS (líquidas de reembolso)
A13: Saúde (médico, dentista, plano) | B13: =SUMIFS(DESPESAS!E6:E105,DESPESAS!A6:A105,"Saúde (médico, dentista, plano)")-SUMIFS(DESPESAS!F6:F105,DESPESAS!A6:A105,"Saúde (médico, dentista, plano)") -> 850
A14: Educação | B14: =SUMIFS(DESPESAS!E6:E105,DESPESAS!A6:A105,"Educação")-SUMIFS(DESPESAS!F6:F105,DESPESAS!A6:A105,"Educação") -> 0
A15: Previdência privada (PGBL) | B15: =SUMIFS(DESPESAS!E6:E105,DESPESAS!A6:A105,"Previdência privada (PGBL)")-SUMIFS(DESPESAS!F6:F105,DESPESAS!A6:A105,"Previdência privada (PGBL)") -> 0
A16: Previdência oficial (INSS) | B16: =SUMIFS(DESPESAS!E6:E105,DESPESAS!A6:A105,"Previdência oficial (INSS)")-SUMIFS(DESPESAS!F6:F105,DESPESAS!A6:A105,"Previdência oficial (INSS)") -> 0
A17: Pensão alimentícia judicial | B17: =SUMIFS(DESPESAS!E6:E105,DESPESAS!A6:A105,"Pensão alimentícia judicial")-SUMIFS(DESPESAS!F6:F105,DESPESAS!A6:A105,"Pensão alimentícia judicial") -> 0
A18: Outros | B18: =SUMIFS(DESPESAS!E6:E105,DESPESAS!A6:A105,"Outros")-SUMIFS(DESPESAS!F6:F105,DESPESAS!A6:A105,"Outros") -> 0
A20: PATRIMÔNIO
A21: Bens e direitos – ano anterior | B21: =SUM(BENS_DIREITOS!C6:C105) -> 45000
A22: Bens e direitos – ano-calendário | B22: =SUM(BENS_DIREITOS!D6:D105) -> 45000
A23: Saldo em contas – ano anterior | B23: =SUM(CONTAS_BANCARIAS!E6:E105) -> 1500
A24: Saldo em contas – ano-calendário | B24: =SUM(CONTAS_BANCARIAS!F6:F105) -> 2300
A26: CONTROLE DE PREENCHIMENTO
A27: Dependentes cadastrados | B27: =COUNTA(DEPENDENTES!A6:A105) -> 1
A28: Fontes pagadoras cadastradas | B28: =COUNTA(RENDIMENTOS!A6:A105) -> 1
A29: Despesas lançadas | B29: =COUNTA(DESPESAS!A6:A105) -> 1
A30: Bens cadastrados | B30: =COUNTA(BENS_DIREITOS!A6:A105) -> 1
A31: Contas bancárias cadastradas | B31: =COUNTA(CONTAS_BANCARIAS!A6:A105) -> 1
A33: Alerta de dependentes | B33: =IF(AND(DADOS_PESSOAIS!B16="Sim",COUNTA(DEPENDENTES!A6:A105)=0),"✘ Cadastre os dependentes",IF(AND(DADOS_PESSOAIS!B16="Não",COUNTA(DEPENDENTES!A6:A105)>0),"✘ Revise: marcou que não há dependentes","✔ Consistente")) -> ✔ Consistente
A35: Valores da linha de exemplo de cada aba entram nestes totais até você substituí-los.

Sheet LINKS_UTEIS
A1: 8. LINKS ÚTEIS
A2: Atalhos para serviços oficiais da Receita Federal.
A3: ◄ Voltar ao Menu
A5: Meu Imposto de Renda (portal oficial) | B5: https://www.gov.br/receitafederal/pt-br/assuntos/meu-imposto-de-renda
A6: Download do programa IRPF | B6: https://www.gov.br/receitafederal/pt-br/centrais-de-conteudo/download/pgd/dirpf
A7: e-CAC – Centro Virtual de Atendimento | B7: https://cav.receita.fazenda.gov.br/
A8: Consulta de situação do CPF | B8: https://servicos.receita.fazenda.gov.br/servicos/cpf/consultasituacao/consultapublica.asp
A9: Consulta de restituição | B9: https://www.restituicao.receita.fazenda.gov.br/
A10: Perguntas e respostas IRPF | B10: https://www.gov.br/receitafederal/pt-br/centrais-de-conteudo/publicacoes/perguntas-e-respostas/dirpf

Sheet APOIO
A1: TABELAS DE APOIO
A2: Listas usadas nas validações. Mantenha esta aba oculta ou protegida.
A3: ◄ Voltar ao Menu
A5: Bancos | B5: Parentesco | C5: TipoRendimento | D5: TipoDespesa | E5: GrupoBem | F5: TipoConta | G5: SimNao
A6: 1 - Banco do Brasil | B6: Cônjuge/Companheiro(a) | C6: Tributável | D6: Saúde (médico, dentista, plano) | E6: 01 - Bens imóveis | F6: Conta corrente | G6: Sim
A7: 102 - XP Investimentos CCTVM S.A. | B7: Filho(a)/Enteado(a) até 21 anos | C7: Isento e não tributável | D7: Educação | E7: 02 - Bens móveis (veículos etc.) | F7: Poupança | G7: Não
A8: 104 - Caixa Econômica Federal | B8: Filho(a)/Enteado(a) universitário até 24 anos | C8: Tributação exclusiva/definitiva | D8: Previdência privada (PGBL) | E8: 03 - Participações societárias | F8: Conta de pagamento
A9: 119 - Banco Western Union do Brasil | B9: Irmão(ã)/Neto(a)/Bisneto(a) | D9: Previdência oficial (INSS) | E9: 04 - Aplicações e investimentos | F9: Investimento
A10: 184 - Banco Itaú BBA S.A. | B10: Pais/Avós/Bisavós | D10: Pensão alimentícia judicial | E10: 05 - Créditos
A11: 197 - Stone Pagamentos | B11: Menor pobre sob guarda judicial | D11: Outros | E11: 06 - Depósitos à vista e numerário
A12: 208 - Banco BTG Pactual | B12: Pessoa absolutamente incapaz | E12: 07 - Fundos
A13: 212 - Banco Original | E13: 08 - Criptoativos
A14: 218 - Banco Bonsucesso | E14: 99 - Outros bens e direitos
A15: 229 - Banco Cruzeiro do Sul
A16: 237 - Banco Bradesco
A17: 24 - Banco de Pernambuco
A18: 241 - Banco Clássico
A19: 250 - Banco de Crédito e Varejo (BCV)
A20: 260 - Nubank
A21: 29 - Banco do Estado do Rio de Janeiro
A22: 290 - PagBank
A23: 3 - Banco da Amazônia
A24: 33 - Banco Santander
A25: 336 - C6 Bank
A26: 341 - Itaú Unibanco
... A55: 82 - Banco Topázio
